setup.py
postopy/__init__.py
postopy/client.py
postopy/config.py
postopy/exception.py
postopy/posto_express.py
postopy.egg-info/PKG-INFO
postopy.egg-info/SOURCES.txt
postopy.egg-info/dependency_links.txt
postopy.egg-info/not-zip-safe
postopy.egg-info/top_level.txt