Metadata-Version: 1.0
Name: postopy
Version: 0.1.1
Summary: Posto Express API in Python
Home-page: https://github.com/mousavian/PostoPy
Author: Rahman Mousavian
Author-email: Mousavian.Rahman@gmail.com
License: MIT
Platform: UNKNOWN
